bow_client/__init__.py
bow_client/bow_client.py
bow_client-4.0.2.2269.data/data/requirements.txt
bow_utils/__init__.py
bow_utils/bow_client_pb2.py
bow_utils/bow_client_pb2.pyi
bow_utils/bow_client_sdk_pb2.py
bow_utils/bow_client_sdk_pb2.pyi
bow_utils/bow_common_pb2.py
bow_utils/bow_common_pb2.pyi
bow_utils/bow_companion_pb2.py
bow_utils/bow_companion_pb2.pyi
bow_utils/bow_data_audio_pb2.py
bow_utils/bow_data_audio_pb2.pyi
bow_utils/bow_data_common_pb2.py
bow_utils/bow_data_common_pb2.pyi
bow_utils/bow_data_exteroception_pb2.py
bow_utils/bow_data_exteroception_pb2.pyi
bow_utils/bow_data_interoception_pb2.py
bow_utils/bow_data_interoception_pb2.pyi
bow_utils/bow_data_motor_pb2.py
bow_utils/bow_data_motor_pb2.pyi
bow_utils/bow_data_octree_pb2.py
bow_utils/bow_data_octree_pb2.pyi
bow_utils/bow_data_pb2.py
bow_utils/bow_data_pb2.pyi
bow_utils/bow_data_tactile_pb2.py
bow_utils/bow_data_tactile_pb2.pyi
bow_utils/bow_data_vision_pb2.py
bow_utils/bow_data_vision_pb2.pyi
bow_utils/bow_messages_pb2.py
bow_utils/bow_messages_pb2.pyi
bow_utils/bow_robot_pb2.py
bow_utils/bow_robot_pb2.pyi
bow_utils/bow_robot_sdk_pb2.py
bow_utils/bow_robot_sdk_pb2.pyi
bow_utils/bow_structs_pb2.py
bow_utils/bow_structs_pb2.pyi
bow_utils/utils.py
lib_client/LICENSE
lib_client/__init__.py
lib_client/_animus_client.so
lib_client/animus_client.py
lib_client/libanimus_client.so
bow_client-4.0.2.2269.dist-info/LICENSE
bow_client-4.0.2.2269.dist-info/METADATA
bow_client-4.0.2.2269.dist-info/WHEEL
bow_client-4.0.2.2269.dist-info/top_level.txt
bow_client-4.0.2.2269.dist-info/RECORD
