Metadata-Version: 2.1
Name: bow-client
Version: 4.0.2.2269
Summary: BOW SDK for Python 3 developed by Bettering Our Worlds (BOW) Ltd.
Home-page: https://www.usebow.com
Author: Daniel Camilleri
Author-email: support@bow.ltd
License: Proprietary. (C) Bettering Our Worlds (BOW) Ltd.
Classifier: Programming Language :: Python
Classifier: Programming Language :: Python :: 3
Classifier: License :: Other/Proprietary License
Classifier: Topic :: Software Development :: Libraries
Classifier: Intended Audience :: Developers
Requires-Python: >=3.7
License-File: LICENSE
Requires-Dist: numpy >=1.16.6
Requires-Dist: numpy <=1.24.4
Requires-Dist: scikit-build
Requires-Dist: opencv-python >=4.2.0.32
Requires-Dist: wheel
Requires-Dist: protobuf ~=4.21
